Stoner/Analysis.py
Stoner/Core.py
Stoner/FileFormats.py
Stoner/Folders.py
Stoner/HDF5.py
Stoner/Util.py
Stoner/Zip.py
Stoner/__init__.py
Stoner/compat.py
Stoner/Image/__init__.py
Stoner/Image/attrs.py
Stoner/Image/core.py
Stoner/Image/folders.py
Stoner/Image/imagefuncs.py
Stoner/Image/kerr.py
Stoner/Image/kerrfuncs.py
Stoner/Image/stack.py
Stoner/Image/util.py
Stoner/Image/widgets.py
Stoner/analysis/__init__.py
Stoner/analysis/columns.py
Stoner/analysis/features.py
Stoner/analysis/filtering.py
Stoner/analysis/utils.py
Stoner/analysis/fitting/__init__.py
Stoner/analysis/fitting/mixins.py
Stoner/analysis/fitting/models/__init__.py
Stoner/analysis/fitting/models/e_transport.py
Stoner/analysis/fitting/models/generic.py
Stoner/analysis/fitting/models/magnetism.py
Stoner/analysis/fitting/models/superconductivity.py
Stoner/analysis/fitting/models/thermal.py
Stoner/analysis/fitting/models/tunnelling.py
Stoner/core/Typing.py
Stoner/core/__init__.py
Stoner/core/array.py
Stoner/core/base.py
Stoner/core/data.py
Stoner/core/exceptions.py
Stoner/core/interfaces.py
Stoner/core/methods.py
Stoner/core/operators.py
Stoner/core/property.py
Stoner/core/setas.py
Stoner/core/utils.py
Stoner/folders/__init__.py
Stoner/folders/core.py
Stoner/folders/each.py
Stoner/folders/groups.py
Stoner/folders/metadata.py
Stoner/folders/mixins.py
Stoner/folders/utils.py
Stoner/formats/__init__.py
Stoner/formats/attocube.py
Stoner/formats/decorators.py
Stoner/formats/maximus.py
Stoner/formats/data/__init__.py
Stoner/formats/data/attocube.py
Stoner/formats/data/facilities.py
Stoner/formats/data/generic.py
Stoner/formats/data/hdf5.py
Stoner/formats/data/instruments.py
Stoner/formats/data/maximus.py
Stoner/formats/data/rigs.py
Stoner/formats/data/simulations.py
Stoner/formats/data/zip.py
Stoner/formats/image/__init__.py
Stoner/formats/image/facilities.py
Stoner/formats/image/generic.py
Stoner/formats/image/hdf5.py
Stoner/formats/image/maximus.py
Stoner/formats/utils/__init__.py
Stoner-0.10.12.dist-info/COPYING
Stoner-0.10.12.dist-info/METADATA
Stoner-0.10.12.dist-info/WHEEL
Stoner-0.10.12.dist-info/top_level.txt
Stoner-0.10.12.dist-info/RECORD
