Metadata-Version: 2.2
Name: Stoner
Version: 0.10.12
Summary: Library to help write data analysis tools for experimental condensed matter physics.
Home-page: http://github.com/~gb119/Stoner-PythonCode
Author: Gavin Burnell
Author-email: g.burnell@leeds.ac.uk
License: GPLv3
Keywords: Data-Analysis Physics
Classifier: Development Status :: 4 - Beta
Classifier: Intended Audience :: Science/Research
Classifier: Topic :: Scientific/Engineering
Classifier: Topic :: Scientific/Engineering :: Physics
Classifier: Operating System :: MacOS :: MacOS X
Classifier: Operating System :: Microsoft :: Windows
Classifier: Operating System :: POSIX
Classifier: Programming Language :: Python :: 3.7
Classifier: Programming Language :: Python :: 3.8
Classifier: Programming Language :: Python :: 3.9
Classifier: Programming Language :: Python :: 3.10
Classifier: License :: OSI Approved :: GNU General Public License v3 (GPLv3)
Requires-Python: >3.7
License-File: COPYING
Requires-Dist: scipy>=1.14
Requires-Dist: numpy>=2.0
Requires-Dist: matplotlib>=3.8
Requires-Dist: scikit-image>=0.24
Requires-Dist: h5py
Requires-Dist: cycler>=0.10.0
Requires-Dist: filemagic>=1.6
Requires-Dist: image-registration>=0.2.1
Requires-Dist: lmfit>=1.3
Requires-Dist: memoization>=0.1.4
Requires-Dist: npTDMS>=1.9.0
Requires-Dist: python-dateutil>=2.7.0
Requires-Dist: statsmodels
Requires-Dist: tabulate>=0.9
Requires-Dist: imreg_dft>=2.0
Requires-Dist: multiprocess>=0.70
Requires-Dist: dill>=0.2.8
Requires-Dist: urllib3>=1.26
Requires-Dist: dateutil>=2.8
Requires-Dist: seaborn>=0.13
Requires-Dist: looseversion>=1.0
Provides-Extra: prettyprint
Requires-Dist: tabulate>=0.7.5; extra == "prettyprint"
Provides-Extra: mimetype-detection
Requires-Dist: magic; extra == "mimetype-detection"
Provides-Extra: tdms
Requires-Dist: nptdms; extra == "tdms"
Provides-Extra: numba
Requires-Dist: numba; extra == "numba"
Provides-Extra: cv2
Requires-Dist: cv2; extra == "cv2"
Provides-Extra: image-alignment
Requires-Dist: imreg_dft; extra == "image-alignment"
Requires-Dist: image_registration; extra == "image-alignment"
Dynamic: author
Dynamic: author-email
Dynamic: classifier
Dynamic: description
Dynamic: home-page
Dynamic: keywords
Dynamic: license
Dynamic: provides-extra
Dynamic: requires-dist
Dynamic: requires-python
Dynamic: summary
